jablotronpy/__init__.py
jablotronpy/jablotronpy.py
JablotronPy-0.10.0.dist-info/LICENSE
JablotronPy-0.10.0.dist-info/METADATA
JablotronPy-0.10.0.dist-info/WHEEL
JablotronPy-0.10.0.dist-info/top_level.txt
JablotronPy-0.10.0.dist-info/RECORD
