Metadata-Version: 2.1
Name: JablotronPy
Version: 0.10.0
Summary: A client to interact with the Jablotron API to control Jablotron alarm systems
Home-page: https://github.com/fdegier/JablotronPy
Author: F. de Gier
Author-email: freddegier@me.com
Requires-Python: >=3.6
License-File: LICENSE
Requires-Dist: requests (>=2.25.0)
